{"v":5,"entries":{"atoms-block--docs":{"id":"atoms-block--docs","title":"Atoms/Block","name":"Docs","importPath":"./src/atomic/atoms/Block.stories.tsx","type":"docs","tags":["dev","test","autodocs"],"storiesImports":[]},"atoms-block--basic":{"type":"story","id":"atoms-block--basic","name":"Basic","title":"Atoms/Block","importPath":"./src/atomic/atoms/Block.stories.tsx","tags":["dev","test","autodocs"]},"atoms-block--with-subtitle":{"type":"story","id":"atoms-block--with-subtitle","name":"With Subtitle","title":"Atoms/Block","importPath":"./src/atomic/atoms/Block.stories.tsx","tags":["dev","test","autodocs"]},"atoms-block--with-footer":{"type":"story","id":"atoms-block--with-footer","name":"With Footer","title":"Atoms/Block","importPath":"./src/atomic/atoms/Block.stories.tsx","tags":["dev","test","autodocs"]},"atoms-block--huge-content-no-scroll":{"type":"story","id":"atoms-block--huge-content-no-scroll","name":"Huge Content No Scroll","title":"Atoms/Block","importPath":"./src/atomic/atoms/Block.stories.tsx","tags":["dev","test","autodocs"]},"atoms-block--huge-content-with-scroll":{"type":"story","id":"atoms-block--huge-content-with-scroll","name":"Huge Content With Scroll","title":"Atoms/Block","importPath":"./src/atomic/atoms/Block.stories.tsx","tags":["dev","test","autodocs"]},"atoms-button--docs":{"id":"atoms-button--docs","title":"Atoms/Button","name":"Docs","importPath":"./src/atomic/atoms/Button.stories.ts","type":"docs","tags":["dev","test","autodocs"],"storiesImports":[]},"atoms-button--basic":{"type":"story","id":"atoms-button--basic","name":"Basic","title":"Atoms/Button","importPath":"./src/atomic/atoms/Button.stories.ts","tags":["dev","test","autodocs"]},"atoms-button--active":{"type":"story","id":"atoms-button--active","name":"Active","title":"Atoms/Button","importPath":"./src/atomic/atoms/Button.stories.ts","tags":["dev","test","autodocs"]},"atoms-button--block":{"type":"story","id":"atoms-button--block","name":"Block","title":"Atoms/Button","importPath":"./src/atomic/atoms/Button.stories.ts","tags":["dev","test","autodocs"]},"atoms-button--disabled":{"type":"story","id":"atoms-button--disabled","name":"Disabled","title":"Atoms/Button","importPath":"./src/atomic/atoms/Button.stories.ts","tags":["dev","test","autodocs"]},"atoms-button--pill":{"type":"story","id":"atoms-button--pill","name":"Pill","title":"Atoms/Button","importPath":"./src/atomic/atoms/Button.stories.ts","tags":["dev","test","autodocs"]},"atoms-button--square":{"type":"story","id":"atoms-button--square","name":"Square","title":"Atoms/Button","importPath":"./src/atomic/atoms/Button.stories.ts","tags":["dev","test","autodocs"]},"atoms-datedisplay--docs":{"id":"atoms-datedisplay--docs","title":"Atoms/DateDisplay","name":"Docs","importPath":"./src/atomic/atoms/DateDisplay.stories.ts","type":"docs","tags":["dev","test","autodocs"],"storiesImports":[]},"atoms-datedisplay--basic":{"type":"story","id":"atoms-datedisplay--basic","name":"Basic","title":"Atoms/DateDisplay","importPath":"./src/atomic/atoms/DateDisplay.stories.ts","tags":["dev","test","autodocs"]},"atoms-keystroke--docs":{"id":"atoms-keystroke--docs","title":"Atoms/Keystroke","name":"Docs","importPath":"./src/atomic/atoms/Keystroke.stories.ts","type":"docs","tags":["dev","test","autodocs"],"storiesImports":[]},"atoms-keystroke--primary":{"type":"story","id":"atoms-keystroke--primary","name":"Primary","title":"Atoms/Keystroke","importPath":"./src/atomic/atoms/Keystroke.stories.ts","tags":["dev","test","autodocs"]},"atoms-loader--docs":{"id":"atoms-loader--docs","title":"Atoms/Loader","name":"Docs","importPath":"./src/atomic/atoms/Loader.stories.ts","type":"docs","tags":["dev","test","autodocs"],"storiesImports":[]},"atoms-loader--basic":{"type":"story","id":"atoms-loader--basic","name":"Basic","title":"Atoms/Loader","importPath":"./src/atomic/atoms/Loader.stories.ts","tags":["dev","test","autodocs"]},"atoms-form-select-field--docs":{"id":"atoms-form-select-field--docs","title":"Atoms/Form/Select Field","name":"Docs","importPath":"./src/atomic/atoms/form/SelectField.stories.ts","type":"docs","tags":["dev","test","autodocs"],"storiesImports":[]},"atoms-form-select-field--basic":{"type":"story","id":"atoms-form-select-field--basic","name":"Basic","title":"Atoms/Form/Select Field","importPath":"./src/atomic/atoms/form/SelectField.stories.ts","tags":["dev","test","autodocs"]},"atoms-form-select-field--with-object":{"type":"story","id":"atoms-form-select-field--with-object","name":"With Object","title":"Atoms/Form/Select Field","importPath":"./src/atomic/atoms/form/SelectField.stories.ts","tags":["dev","test","autodocs"]},"atoms-form-square-colorpicker--docs":{"id":"atoms-form-square-colorpicker--docs","title":"Atoms/Form/Square Colorpicker","name":"Docs","importPath":"./src/atomic/atoms/form/SquareColorpicker.stories.ts","type":"docs","tags":["dev","test","autodocs"],"storiesImports":[]},"atoms-form-square-colorpicker--basic":{"type":"story","id":"atoms-form-square-colorpicker--basic","name":"Basic","title":"Atoms/Form/Square Colorpicker","importPath":"./src/atomic/atoms/form/SquareColorpicker.stories.ts","tags":["dev","test","autodocs"]},"molecules-modal--docs":{"id":"molecules-modal--docs","title":"Molecules/Modal","name":"Docs","importPath":"./src/atomic/molecules/Modal.stories.ts","type":"docs","tags":["dev","test","autodocs"],"storiesImports":[]},"molecules-modal--basic":{"type":"story","id":"molecules-modal--basic","name":"Basic","title":"Molecules/Modal","importPath":"./src/atomic/molecules/Modal.stories.ts","tags":["dev","test","autodocs"]},"molecules-form-integer-field--docs":{"id":"molecules-form-integer-field--docs","title":"Molecules/Form/Integer Field","name":"Docs","importPath":"./src/atomic/molecules/form/IntegerField.stories.ts","type":"docs","tags":["dev","test","autodocs"],"storiesImports":[]},"molecules-form-integer-field--basic":{"type":"story","id":"molecules-form-integer-field--basic","name":"Basic","title":"Molecules/Form/Integer Field","importPath":"./src/atomic/molecules/form/IntegerField.stories.ts","tags":["dev","test","autodocs"]},"molecules-navigator-tab--docs":{"id":"molecules-navigator-tab--docs","title":"Molecules/Navigator/Tab","name":"Docs","importPath":"./src/atomic/molecules/navigator/NavigatorTab.stories.ts","type":"docs","tags":["dev","test","autodocs"],"storiesImports":[]},"molecules-navigator-tab--basic":{"type":"story","id":"molecules-navigator-tab--basic","name":"Basic","title":"Molecules/Navigator/Tab","importPath":"./src/atomic/molecules/navigator/NavigatorTab.stories.ts","tags":["dev","test","autodocs"]},"molecules-navigator-tab--with-prev-next":{"type":"story","id":"molecules-navigator-tab--with-prev-next","name":"With Prev Next","title":"Molecules/Navigator/Tab","importPath":"./src/atomic/molecules/navigator/NavigatorTab.stories.ts","tags":["dev","test","autodocs"]},"molecules-navigator-tab--expanded":{"type":"story","id":"molecules-navigator-tab--expanded","name":"Expanded","title":"Molecules/Navigator/Tab","importPath":"./src/atomic/molecules/navigator/NavigatorTab.stories.ts","tags":["dev","test","autodocs"]},"organisms-tabs--docs":{"id":"organisms-tabs--docs","title":"Organisms/Tabs","name":"Docs","importPath":"./src/atomic/organisms/Tabs.stories.tsx","type":"docs","tags":["dev","test","autodocs"],"storiesImports":[]},"organisms-tabs--basic":{"type":"story","id":"organisms-tabs--basic","name":"Basic","title":"Organisms/Tabs","importPath":"./src/atomic/organisms/Tabs.stories.tsx","tags":["dev","test","autodocs"]},"organisms-tabs--with-prev-next":{"type":"story","id":"organisms-tabs--with-prev-next","name":"With Prev Next","title":"Organisms/Tabs","importPath":"./src/atomic/organisms/Tabs.stories.tsx","tags":["dev","test","autodocs"]},"organisms-tabs--expanded":{"type":"story","id":"organisms-tabs--expanded","name":"Expanded","title":"Organisms/Tabs","importPath":"./src/atomic/organisms/Tabs.stories.tsx","tags":["dev","test","autodocs"]},"organisms-layout-fullscreen-app--simple":{"type":"story","id":"organisms-layout-fullscreen-app--simple","name":"Simple","title":"Organisms/Layout/Fullscreen App","importPath":"./src/atomic/organisms/layout/FullscreenApp.stories.tsx","tags":["dev","test"]},"organisms-layout-fullscreen-app--full":{"type":"story","id":"organisms-layout-fullscreen-app--full","name":"Full","title":"Organisms/Layout/Fullscreen App","importPath":"./src/atomic/organisms/layout/FullscreenApp.stories.tsx","tags":["dev","test"]}}}
